{
  "$schema": "https://biomejs.dev/schemas/2.0.6/schema.json",
  "vcs": {
    "enabled": true,
    "clientKind": "git",
    "useIgnoreFile": true
  },
  "formatter": {
    "enabled": true,
    "formatWithErrors": false,
    "indentStyle": "space",
    "indentWidth": 2,
    "lineEnding": "lf",
    "lineWidth": 100,
    "attributePosition": "auto"
  },
  "linter": {
    "enabled": true,
    "rules": {
      "recommended": true,
      "complexity": {
        "noForEach": "off",
        "useArrowFunction": "error"
      },
      "correctness": {
        "noUnusedImports": "error",
        "noUnusedVariables": "error",
        "useExhaustiveDependencies": "warn"
      },
      "style": {
        "noNonNullAssertion": "off",
        "useConst": "error",
        "useNodejsImportProtocol": "off"
      },
      "suspicious": {
        "noExplicitAny": "warn",
        "noArrayIndexKey": "warn"
      }
    }
  },
  "javascript": {
    "formatter": {
      "quoteStyle": "single",
      "jsxQuoteStyle": "double",
      "semicolons": "always",
      "trailingCommas": "es5",
      "arrowParentheses": "always",
      "bracketSpacing": true,
      "bracketSameLine": false
    }
  },
  "files": {
    "ignoreUnknown": false,
    "experimentalScannerIgnores": [
      "node_modules",
      "dist",
      "build",
      ".next",
      "src-tauri/target",
      "src-tauri/Cargo.lock"
    ]
  }
}
